dokushin/__init__.py
dokushin-0.1.0.dist-info/LICENSE
dokushin-0.1.0.dist-info/METADATA
dokushin-0.1.0.dist-info/WHEEL
dokushin-0.1.0.dist-info/RECORD
